swinlnk
