Metadata-Version: 1.1
Name: swinlnk
Version: 0.1.3
Summary: Create windows shortcuts (.lnk files) from anywhere
Home-page: http://github.com/bristi/swinlnk
Author: Brian Stidsen
Author-email: brianstidsen@gmail.com
License: MIT
Keywords: lnk
Platform: UNKNOWN
Classifier: Development Status :: 3 - Alpha
Classifier: Intended Audience :: Developers
Classifier: License :: OSI Approved :: MIT License
Classifier: Programming Language :: Python :: 3
Classifier: Topic :: Software Development :: Libraries
